Metadata-Version: 2.1
Name: embedpy
Version: 2.1.0
Summary: Python client library for Cowrywise Embed Investments API
Home-page: https://github.com/cowrywise/embedpy
Author: Cowrywise Developers
Author-email: embed@cowrywise.com
License: MIT
Keywords: cowrywise,embedpy
Platform: UNKNOWN
License-File: LICENSE
Requires-Dist: requests
Requires-Dist: pytest
Requires-Dist: pytest-mock
